{
  "version": "1.0.0",
  "restore": {
    "projectUniqueName": "D:\\Repo\\Socketize\\Socketize\\Socketize.csproj",
    "projectName": "Socketize",
    "projectPath": "D:\\Repo\\Socketize\\Socketize\\Socketize.csproj",
    "outputPath": "D:\\Repo\\Socketize\\Socketize\\obj\\",
    "projectStyle": "PackageReference",
    "fallbackFolders": [
      "C:\\Program Files\\dotnet\\sdk\\NuGetFallbackFolder"
    ],
    "originalTargetFrameworks": [
      "netstandard2.0"
    ],
    "sources": {
      "https://api.nuget.org/v3/index.json": {},
      "https://proget.x-plarium.com/nuget/plarium": {}
    },
    "frameworks": {
      "netstandard2.0": {
        "projectReferences": {}
      }
    },
    "warningProperties": {
      "warnAsError": [
        "NU1605"
      ]
    }
  },
  "frameworks": {
    "netstandard2.0": {
      "dependencies": {
        "Lidgren.Network": {
          "target": "Package",
          "version": "[1.0.2, )"
        },
        "Microsoft.Extensions.Logging.Abstractions": {
          "target": "Package",
          "version": "[2.2.0, )"
        },
        "NETStandard.Library": {
          "suppressParent": "All",
          "target": "Package",
          "version": "[2.0.3, )",
          "autoReferenced": true
        },
        "Newtonsoft.Json": {
          "target": "Package",
          "version": "[12.0.2, )"
        },
        "ZeroFormatter": {
          "target": "Package",
          "version": "[1.6.4, )"
        }
      },
      "imports": [
        "net461"
      ],
      "assetTargetFallback": true,
      "warn": true
    }
  }
}